Extract.py
main.py
setup.py
DataExpress.egg-info/PKG-INFO
DataExpress.egg-info/SOURCES.txt
DataExpress.egg-info/dependency_links.txt
DataExpress.egg-info/top_level.txt